delia/__init__.py
delia/databases/__init__.py
delia/databases/patients_database.py
delia/extractors/__init__.py
delia/extractors/patients_data_extractor.py
delia/radiomics/__init__.py
delia/radiomics/radiomics_dataset.py
delia/readers/__init__.py
delia/readers/image/__init__.py
delia/readers/image/dicom_reader.py
delia/readers/patient_data/__init__.py
delia/readers/patient_data/patient_data_query_context.py
delia/readers/patient_data/patient_data_query_strategy.py
delia/readers/patient_data/patient_data_reader.py
delia/readers/patient_data/factories/__init__.py
delia/readers/patient_data/factories/base_patient_data_factory.py
delia/readers/patient_data/factories/patient_data_factories.py
delia/readers/segmentation/__init__.py
delia/readers/segmentation/segmentation_context.py
delia/readers/segmentation/segmentation_reader.py
delia/readers/segmentation/segmentation_strategy.py
delia/readers/segmentation/factories/__init__.py
delia/readers/segmentation/factories/base_segmentation_factory.py
delia/readers/segmentation/factories/dicom_segmentation_factories.py
delia/readers/segmentation/factories/segment.py
delia/readers/segmentation/factories/segmentation.py
delia/transforms/__init__.py
delia/transforms/applications.py
delia/transforms/tools.py
delia/transforms/array_space/__init__.py
delia/transforms/array_space/matching_centroid_spatial_crop.py
delia/transforms/array_space/matching_crop_foreground.py
delia/transforms/array_space/tools.py
delia/transforms/array_space/transform.py
delia/transforms/data/__init__.py
delia/transforms/data/copy_segmentations.py
delia/transforms/data/transform.py
delia/transforms/physical_space/__init__.py
delia/transforms/physical_space/matching_resample.py
delia/transforms/physical_space/pet_to_suv.py
delia/transforms/physical_space/resample.py
delia/transforms/physical_space/transform.py
delia/utils/__init__.py
delia/utils/data_model.py
delia/utils/tools.py
delia/utils/transforms_history.py
examples/__init__.py
examples/env_examples.py
delia-1.2.7.dist-info/LICENSE
delia-1.2.7.dist-info/METADATA
delia-1.2.7.dist-info/WHEEL
delia-1.2.7.dist-info/top_level.txt
delia-1.2.7.dist-info/RECORD
