Metadata-Version: 2.1
Name: delia
Version: 1.2.7
Summary: DICOM Extraction for Large-scale Image Analysis (DELIA).
Home-page: https://github.com/MaxenceLarose/delia
Author: Maxence Larose
Author-email: maxence.larose.1@ulaval.ca
License: Apache License 2.0
Keywords: dicom hdf5 medical image segmentation pre-processing python3 radiomics deep-learning dicom-seg rt-struct
Classifier: Programming Language :: Python :: 3
Classifier: License :: OSI Approved :: Apache Software License
Classifier: Operating System :: OS Independent
Requires-Python: >=3.7
License-File: LICENSE
Requires-Dist: h5py
Requires-Dist: monai ==1.0.1
Requires-Dist: numpy
Requires-Dist: pandas
Requires-Dist: pydicom
Requires-Dist: pydicom-seg
Requires-Dist: rt-utils
Requires-Dist: scikit-image
Requires-Dist: SimpleITK
